{"cameraMode":{"drawMode":0,"name":"Shaded","section":"Shading Mode"},"sceneLighting":true,"audioPlay":false,"sceneViewState":{"m_AlwaysRefresh":false,"showFog":true,"showSkybox":true,"showFlares":true,"showImageEffects":true,"showParticleSystems":true,"showVisualEffectGraphs":true,"m_FxEnabled":true},"in2DMode":false,"pivot":{"x":0.060716867446899417,"y":0.7424466609954834,"z":-0.49255120754241946},"rotation":{"x":0.3336036801338196,"y":-0.5965763926506043,"z":0.29884791374206545,"w":0.6659565567970276},"size":1.8629287481307984,"orthographic":false}